pysensu_yelp/__init__.py
pysensu_yelp/py.typed
pysensu_yelp-1.0.3.dist-info/LICENSE
pysensu_yelp-1.0.3.dist-info/METADATA
pysensu_yelp-1.0.3.dist-info/WHEEL
pysensu_yelp-1.0.3.dist-info/top_level.txt
pysensu_yelp-1.0.3.dist-info/RECORD
