Metadata-Version: 2.1
Name: pysensu-yelp
Version: 1.0.3
Summary: Emits Yelp-flavored Sensu events to a Sensu Client
Home-page: https://github.com/Yelp/pysensu-yelp
Author: Yelp Operations Team
Author-email: operations@yelp.com
License: Apache License 2.0
Platform: UNKNOWN
Classifier: Programming Language :: Python :: 3
Classifier: Programming Language :: Python :: 3.6
Classifier: Programming Language :: Python :: 3.7
Classifier: Programming Language :: Python :: 3.8
Provides: pysensu_yelp
Requires-Python: >=3.6
